dianaensias/__init__.py
dianaensias/dianaensias.py
dianaensias-0.0.2.dist-info/LICENSE
dianaensias-0.0.2.dist-info/METADATA
dianaensias-0.0.2.dist-info/WHEEL
dianaensias-0.0.2.dist-info/top_level.txt
dianaensias-0.0.2.dist-info/RECORD
