Metadata-Version: 2.1
Name: dianaensias
Version: 0.0.2
Summary: diana algorithme for ensias
Home-page: https://github.com/pypa/sampleproject
Author: Kirwa Takadi
Author-email: me@kirwako.com
License: UNKNOWN
Project-URL: Bug Tracker, https://github.com/pypa/sampleproject/issues
Platform: UNKNOWN
Classifier: Programming Language :: Python :: 3
Classifier: License :: OSI Approved :: MIT License
Classifier: Operating System :: OS Independent
Requires-Python: >=3.6
License-File: LICENSE
